{
  "kind": "youtube#searchListResponse",
  "etag": "uP-m1u0usIQ8XYvlYLiR1Ytv9KI",
  "nextPageToken": "CB4QAA",
  "regionCode": "IN",
  "pageInfo": {
    "totalResults": 1000000,
    "resultsPerPage": 30
  },
  "items": [
    {
      "kind": "youtube#searchResult",
      "etag": "ArRu--RhNLSwbe3BFBnSIlzk6pY",
      "id": {
        "kind": "youtube#video",
        "videoId": "zOjov-2OZ0E"
      },
      "snippet": {
        "publishedAt": "2020-04-21T13:45:02Z",
        "channelId": "UC8butISFwT-Wl7EV0hUK0BQ",
        "title": "Introduction to Programming and Computer Science - Full Course",
        "description": "In this course, you will learn basics of computer programming and computer science. The concepts you learn apply to any and all ...",
        "thumbnails": {
          "default": {
            "url": "https://i.ytimg.com/vi/zOjov-2OZ0E/default.jpg",
            "width": 120,
            "height": 90
          },
          "medium": {
            "url": "https://i.ytimg.com/vi/zOjov-2OZ0E/mqdefault.jpg",
            "width": 320,
            "height": 180
          },
          "high": {
            "url": "https://i.ytimg.com/vi/zOjov-2OZ0E/hqdefault.jpg",
            "width": 480,
            "height": 360
          }
        },
        "channelTitle": "freeCodeCamp.org",
        "liveBroadcastContent": "none",
        "publishTime": "2020-04-21T13:45:02Z"
      }
    },
    {
      "kind": "youtube#searchResult",
      "etag": "_PmgQsDdfD8wnUOVGp8LC78witk",
      "id": {
        "kind": "youtube#video",
        "videoId": "EByDFE6zFPU"
      },
      "snippet": {
        "publishedAt": "2020-09-28T11:30:11Z",
        "channelId": "UCN3-BVMnr44LIUheSuppw1A",
        "title": "How to learn Programming Language With Full Information? – [Hindi] – Quick Support",
        "description": "HowtolearnProgrammingLanguage #QuickSupport How to learn Programming Language With Full Information? – [Hindi] – Quick ...",
        "thumbnails": {
          "default": {
            "url": "https://i.ytimg.com/vi/EByDFE6zFPU/default.jpg",
            "width": 120,
            "height": 90
          },
          "medium": {
            "url": "https://i.ytimg.com/vi/EByDFE6zFPU/mqdefault.jpg",
            "width": 320,
            "height": 180
          },
          "high": {
            "url": "https://i.ytimg.com/vi/EByDFE6zFPU/hqdefault.jpg",
            "width": 480,
            "height": 360
          }
        },
        "channelTitle": "Quick Support",
        "liveBroadcastContent": "none",
        "publishTime": "2020-09-28T11:30:11Z"
      }
    },
    {
      "kind": "youtube#searchResult",
      "etag": "XEkmGzA2xwjSdr8UpqVIpIrA2LU",
      "id": {
        "kind": "youtube#video",
        "videoId": "eKqY-oP1d_Y"
      },
      "snippet": {
        "publishedAt": "2022-01-25T17:54:00Z",
        "channelId": "UCBwmMxybNva6P_5VmxjzwqA",
        "title": "How to Start Coding? Learn Programming for Beginners",
        "description": "Java Placement Course : https://www.youtube.com/watch?v=yRpLlJmRo2w&list=PLfqMhTWNBTe3LtFWcvwpqTkUSlB32kJop ...",
        "thumbnails": {
          "default": {
            "url": "https://i.ytimg.com/vi/eKqY-oP1d_Y/default.jpg",
            "width": 120,
            "height": 90
          },
          "medium": {
            "url": "https://i.ytimg.com/vi/eKqY-oP1d_Y/mqdefault.jpg",
            "width": 320,
            "height": 180
          },
          "high": {
            "url": "https://i.ytimg.com/vi/eKqY-oP1d_Y/hqdefault.jpg",
            "width": 480,
            "height": 360
          }
        },
        "channelTitle": "Apna College",
        "liveBroadcastContent": "none",
        "publishTime": "2022-01-25T17:54:00Z"
      }
    },
    {
      "kind": "youtube#searchResult",
      "etag": "JwvP1bq1zgURApDvoGN8tUsqUps",
      "id": {
        "kind": "youtube#video",
        "videoId": "_uQrJ0TkZlc"
      },
      "snippet": {
        "publishedAt": "2019-02-18T15:00:08Z",
        "channelId": "UCWv7vMbMWH4-V0ZXdmDpPBA",
        "title": "Python Tutorial - Python Full Course for Beginners",
        "description": "Python tutorial - Python full course for beginners - Go from Zero to Hero with Python (includes machine learning & web ...",
        "thumbnails": {
          "default": {
            "url": "https://i.ytimg.com/vi/_uQrJ0TkZlc/default.jpg",
            "width": 120,
            "height": 90
          },
          "medium": {
            "url": "https://i.ytimg.com/vi/_uQrJ0TkZlc/mqdefault.jpg",
            "width": 320,
            "height": 180
          },
          "high": {
            "url": "https://i.ytimg.com/vi/_uQrJ0TkZlc/hqdefault.jpg",
            "width": 480,
            "height": 360
          }
        },
        "channelTitle": "Programming with Mosh",
        "liveBroadcastContent": "none",
        "publishTime": "2019-02-18T15:00:08Z"
      }
    },
    {
      "kind": "youtube#searchResult",
      "etag": "mLJkh0FCHgufNypblSkt97HinVc",
      "id": {
        "kind": "youtube#video",
        "videoId": "VSEnzzjAm0c"
      },
      "snippet": {
        "publishedAt": "2021-05-06T05:03:19Z",
        "channelId": "UCV7cZwHMX_0vk8DSYrS7GCg",
        "title": "C Programming Full Course for Beginners (Hindi) | Learn Coding",
        "description": "इस एक video में मैने C Programming को Basic से Advance तक बताया है, जिसमें हमने C ...",
        "thumbnails": {
          "default": {
            "url": "https://i.ytimg.com/vi/VSEnzzjAm0c/default.jpg",
            "width": 120,
            "height": 90
          },
          "medium": {
            "url": "https://i.ytimg.com/vi/VSEnzzjAm0c/mqdefault.jpg",
            "width": 320,
            "height": 180
          },
          "high": {
            "url": "https://i.ytimg.com/vi/VSEnzzjAm0c/hqdefault.jpg",
            "width": 480,
            "height": 360
          }
        },
        "channelTitle": "Learn Coding",
        "liveBroadcastContent": "none",
        "publishTime": "2021-05-06T05:03:19Z"
      }
    },
    {
      "kind": "youtube#searchResult",
      "etag": "iNA23zdimZ96knxsREaCxeWqpok",
      "id": {
        "kind": "youtube#video",
        "videoId": "UXVoAfcN4E4"
      },
      "snippet": {
        "publishedAt": "2019-03-30T13:57:49Z",
        "channelId": "UC3Q1y6PHeoKBvZuaoJ4PrWw",
        "title": "What is Programming?, Where it is used?? | प्रोग्रामिंग क्या है ?, इसका उपयोग कहाँ किया जाता है ??",
        "description": "A programming language is a formal language, which comprises a set of instructions that produce various kinds of output.",
        "thumbnails": {
          "default": {
            "url": "https://i.ytimg.com/vi/UXVoAfcN4E4/default.jpg",
            "width": 120,
            "height": 90
          },
          "medium": {
            "url": "https://i.ytimg.com/vi/UXVoAfcN4E4/mqdefault.jpg",
            "width": 320,
            "height": 180
          },
          "high": {
            "url": "https://i.ytimg.com/vi/UXVoAfcN4E4/hqdefault.jpg",
            "width": 480,
            "height": 360
          }
        },
        "channelTitle": "Niket Shah Plus",
        "liveBroadcastContent": "none",
        "publishTime": "2019-03-30T13:57:49Z"
      }
    },
    {
      "kind": "youtube#searchResult",
      "etag": "WE7QBTN40cZtU57zf-IWBts767M",
      "id": {
        "kind": "youtube#video",
        "videoId": "HIj8wU_rGIU"
      },
      "snippet": {
        "publishedAt": "2020-02-25T15:43:31Z",
        "channelId": "UCCktnahuRFYIBtNnKT5IYyg",
        "title": "How to Start Coding | Programming for Beginners | Learn Coding | Intellipaat",
        "description": "Intellipaat Python course: https://intellipaat.com/python-for-data-science-training/ Intellipaat Programming courses: ...",
        "thumbnails": {
          "default": {
            "url": "https://i.ytimg.com/vi/HIj8wU_rGIU/default.jpg",
            "width": 120,
            "height": 90
          },
          "medium": {
            "url": "https://i.ytimg.com/vi/HIj8wU_rGIU/mqdefault.jpg",
            "width": 320,
            "height": 180
          },
          "high": {
            "url": "https://i.ytimg.com/vi/HIj8wU_rGIU/hqdefault.jpg",
            "width": 480,
            "height": 360
          }
        },
        "channelTitle": "Intellipaat",
        "liveBroadcastContent": "none",
        "publishTime": "2020-02-25T15:43:31Z"
      }
    },
    {
      "kind": "youtube#searchResult",
      "etag": "nz6X1oVpHsWlm4L3JGphqMrcpX8",
      "id": {
        "kind": "youtube#video",
        "videoId": "CIRGjwYgdT4"
      },
      "snippet": {
        "publishedAt": "2021-02-25T08:56:12Z",
        "channelId": "UCRLEADhMcb8WUdnQ5_Alk7g",
        "title": "Programming vs Coding - What&#39;s the difference?",
        "description": "Programming vs coding -- my take on the difference. If you're serious about learning & earning money with coding Visit ...",
        "thumbnails": {
          "default": {
            "url": "https://i.ytimg.com/vi/CIRGjwYgdT4/default.jpg",
            "width": 120,
            "height": 90
          },
          "medium": {
            "url": "https://i.ytimg.com/vi/CIRGjwYgdT4/mqdefault.jpg",
            "width": 320,
            "height": 180
          },
          "high": {
            "url": "https://i.ytimg.com/vi/CIRGjwYgdT4/hqdefault.jpg",
            "width": 480,
            "height": 360
          }
        },
        "channelTitle": "Aaron Jack / Freemote",
        "liveBroadcastContent": "none",
        "publishTime": "2021-02-25T08:56:12Z"
      }
    },
    {
      "kind": "youtube#searchResult",
      "etag": "OULpoKI5-XamAyHy63O4dKnA35A",
      "id": {
        "kind": "youtube#video",
        "videoId": "U8_8fTODn5g"
      },
      "snippet": {
        "publishedAt": "2018-07-27T12:24:26Z",
        "channelId": "UC1tVU8H153ZFO9eRsxdJlhA",
        "title": "Learn C language in 30 Minutes &amp; Start Coding For Beginners in Hindi",
        "description": "how to start coding and learn coding and become a computer programmer easy step by step guide and tutorials for beginners to ...",
        "thumbnails": {
          "default": {
            "url": "https://i.ytimg.com/vi/U8_8fTODn5g/default.jpg",
            "width": 120,
            "height": 90
          },
          "medium": {
            "url": "https://i.ytimg.com/vi/U8_8fTODn5g/mqdefault.jpg",
            "width": 320,
            "height": 180
          },
          "high": {
            "url": "https://i.ytimg.com/vi/U8_8fTODn5g/hqdefault.jpg",
            "width": 480,
            "height": 360
          }
        },
        "channelTitle": "Technology Gyan",
        "liveBroadcastContent": "none",
        "publishTime": "2018-07-27T12:24:26Z"
      }
    },
    {
      "kind": "youtube#searchResult",
      "etag": "8UmYeZ5D9j7NafPHc86RCcRzqDM",
      "id": {
        "kind": "youtube#video",
        "videoId": "Dv7gLpW91DM"
      },
      "snippet": {
        "publishedAt": "2014-01-01T12:14:38Z",
        "channelId": "UCpzRThdQ1qbWVvBQXXZ2rCA",
        "title": "Why Programming Is Important?",
        "description": "This is a code.org video that explains everything we should know and do. PS: I do not own this video. I shared it just to spread the ...",
        "thumbnails": {
          "default": {
            "url": "https://i.ytimg.com/vi/Dv7gLpW91DM/default.jpg",
            "width": 120,
            "height": 90
          },
          "medium": {
            "url": "https://i.ytimg.com/vi/Dv7gLpW91DM/mqdefault.jpg",
            "width": 320,
            "height": 180
          },
          "high": {
            "url": "https://i.ytimg.com/vi/Dv7gLpW91DM/hqdefault.jpg",
            "width": 480,
            "height": 360
          }
        },
        "channelTitle": "Bugra Kilic",
        "liveBroadcastContent": "none",
        "publishTime": "2014-01-01T12:14:38Z"
      }
    },
    {
      "kind": "youtube#searchResult",
      "etag": "GigBLhf8lgbXxH7JDSCb-0mR7Vs",
      "id": {
        "kind": "youtube#video",
        "videoId": "LBoyofE1mQw"
      },
      "snippet": {
        "publishedAt": "2022-04-07T16:08:10Z",
        "channelId": "UCsQ6_w5iUOUOMAUPclg2kcg",
        "title": "Best Mobile Apps to Learn Programming | Programmer बनो! | C++, Java, Python &amp; More!",
        "description": "Coding/Programing Kaise sikhe? Learn to code with a Phone. Dosto! ish video ham 10 aise Mobile apps/websites janege jo apko ...",
        "thumbnails": {
          "default": {
            "url": "https://i.ytimg.com/vi/LBoyofE1mQw/default.jpg",
            "width": 120,
            "height": 90
          },
          "medium": {
            "url": "https://i.ytimg.com/vi/LBoyofE1mQw/mqdefault.jpg",
            "width": 320,
            "height": 180
          },
          "high": {
            "url": "https://i.ytimg.com/vi/LBoyofE1mQw/hqdefault.jpg",
            "width": 480,
            "height": 360
          }
        },
        "channelTitle": "Skillsiya",
        "liveBroadcastContent": "none",
        "publishTime": "2022-04-07T16:08:10Z"
      }
    },
    {
      "kind": "youtube#searchResult",
      "etag": "3Eg7KWhviBlw4XHn-eO6MGgKKPc",
      "id": {
        "kind": "youtube#video",
        "videoId": "KJgsSFOSQv0"
      },
      "snippet": {
        "publishedAt": "2018-08-15T17:52:20Z",
        "channelId": "UC8butISFwT-Wl7EV0hUK0BQ",
        "title": "C Programming Tutorial for Beginners",
        "description": "This course will give you a full introduction into all of the core concepts in the C programming language. Want more from Mike?",
        "thumbnails": {
          "default": {
            "url": "https://i.ytimg.com/vi/KJgsSFOSQv0/default.jpg",
            "width": 120,
            "height": 90
          },
          "medium": {
            "url": "https://i.ytimg.com/vi/KJgsSFOSQv0/mqdefault.jpg",
            "width": 320,
            "height": 180
          },
          "high": {
            "url": "https://i.ytimg.com/vi/KJgsSFOSQv0/hqdefault.jpg",
            "width": 480,
            "height": 360
          }
        },
        "channelTitle": "freeCodeCamp.org",
        "liveBroadcastContent": "none",
        "publishTime": "2018-08-15T17:52:20Z"
      }
    },
    {
      "kind": "youtube#searchResult",
      "etag": "uvviz4Pf3-RKntcBCOTRzTW-iOc",
      "id": {
        "kind": "youtube#video",
        "videoId": "YZYKrG6PzjI"
      },
      "snippet": {
        "publishedAt": "2021-05-12T01:53:26Z",
        "channelId": "UCV7cZwHMX_0vk8DSYrS7GCg",
        "title": "Difference between Coding and Programming | Learn Coding",
        "description": "C Programming Full Course का video Link है ये वाला, इसे भी एक बार जरूर देखे ...",
        "thumbnails": {
          "default": {
            "url": "https://i.ytimg.com/vi/YZYKrG6PzjI/default.jpg",
            "width": 120,
            "height": 90
          },
          "medium": {
            "url": "https://i.ytimg.com/vi/YZYKrG6PzjI/mqdefault.jpg",
            "width": 320,
            "height": 180
          },
          "high": {
            "url": "https://i.ytimg.com/vi/YZYKrG6PzjI/hqdefault.jpg",
            "width": 480,
            "height": 360
          }
        },
        "channelTitle": "Learn Coding",
        "liveBroadcastContent": "none",
        "publishTime": "2021-05-12T01:53:26Z"
      }
    },
    {
      "kind": "youtube#searchResult",
      "etag": "begMkKvub7mV-LJbFig40psKDo0",
      "id": {
        "kind": "youtube#video",
        "videoId": "bJzb-RuUcMU"
      },
      "snippet": {
        "publishedAt": "2018-11-04T01:12:12Z",
        "channelId": "UCfuSelBtnyCACv0KjG2P1-A",
        "title": "How To Learn Programming for BEGINNERS! (2019/2020)",
        "description": "This simple tutorial will teach you how you can learn computer programming and teach yourself code. Learning code is not that ...",
        "thumbnails": {
          "default": {
            "url": "https://i.ytimg.com/vi/bJzb-RuUcMU/default.jpg",
            "width": 120,
            "height": 90
          },
          "medium": {
            "url": "https://i.ytimg.com/vi/bJzb-RuUcMU/mqdefault.jpg",
            "width": 320,
            "height": 180
          },
          "high": {
            "url": "https://i.ytimg.com/vi/bJzb-RuUcMU/hqdefault.jpg",
            "width": 480,
            "height": 360
          }
        },
        "channelTitle": "CroatCode",
        "liveBroadcastContent": "none",
        "publishTime": "2018-11-04T01:12:12Z"
      }
    },
    {
      "kind": "youtube#searchResult",
      "etag": "uKf9p6OEDxL8p7S09iFMz1EtjmQ",
      "id": {
        "kind": "youtube#video",
        "videoId": "sW9npZVpiMI"
      },
      "snippet": {
        "publishedAt": "2021-01-06T01:05:51Z",
        "channelId": "UCV0qA-eDDICsRR9rPcnG7tw",
        "title": "why you NEED math for programming",
        "description": "Get the JomaClass membership: https://joma.tech/38wHNoq First 100 people get 15% off the yearly subscription with promo code ...",
        "thumbnails": {
          "default": {
            "url": "https://i.ytimg.com/vi/sW9npZVpiMI/default.jpg",
            "width": 120,
            "height": 90
          },
          "medium": {
            "url": "https://i.ytimg.com/vi/sW9npZVpiMI/mqdefault.jpg",
            "width": 320,
            "height": 180
          },
          "high": {
            "url": "https://i.ytimg.com/vi/sW9npZVpiMI/hqdefault.jpg",
            "width": 480,
            "height": 360
          }
        },
        "channelTitle": "Joma Tech",
        "liveBroadcastContent": "none",
        "publishTime": "2021-01-06T01:05:51Z"
      }
    },
    {
      "kind": "youtube#searchResult",
      "etag": "0wGOkgeN2_wG9zYTdsgcCDKAXIE",
      "id": {
        "kind": "youtube#video",
        "videoId": "FrFY6Y1MJBQ"
      },
      "snippet": {
        "publishedAt": "2021-04-25T21:06:10Z",
        "channelId": "UCkCJ0zLrSg7VudR97g-FNVQ",
        "title": "Self Taught Programmers... Listen Up.",
        "description": "Special deal! Every purchase of a 2-year plan will get you 1 additional month free. Go to https://www.nordvpn.com/gunderman or ...",
        "thumbnails": {
          "default": {
            "url": "https://i.ytimg.com/vi/FrFY6Y1MJBQ/default.jpg",
            "width": 120,
            "height": 90
          },
          "medium": {
            "url": "https://i.ytimg.com/vi/FrFY6Y1MJBQ/mqdefault.jpg",
            "width": 320,
            "height": 180
          },
          "high": {
            "url": "https://i.ytimg.com/vi/FrFY6Y1MJBQ/hqdefault.jpg",
            "width": 480,
            "height": 360
          }
        },
        "channelTitle": "Kenny Gunderman",
        "liveBroadcastContent": "none",
        "publishTime": "2021-04-25T21:06:10Z"
      }
    },
    {
      "kind": "youtube#searchResult",
      "etag": "MXlzVk8zxs_0y67KTgDsq6B6ZOA",
      "id": {
        "kind": "youtube#video",
        "videoId": "Df1sbXrLVx4"
      },
      "snippet": {
        "publishedAt": "2020-08-16T12:39:20Z",
        "channelId": "UC1tVU8H153ZFO9eRsxdJlhA",
        "title": "खतरनाक Hacker बनना है तो ये जरूर सीखे 😲😲| Which Programming Languages Do HACKERS Use &amp; Why ??",
        "description": "Which Top Programming Language do hackers use & Why : Well aap sabhi logo ne hacker ke bare mein suna hi hoga , kya aap ...",
        "thumbnails": {
          "default": {
            "url": "https://i.ytimg.com/vi/Df1sbXrLVx4/default.jpg",
            "width": 120,
            "height": 90
          },
          "medium": {
            "url": "https://i.ytimg.com/vi/Df1sbXrLVx4/mqdefault.jpg",
            "width": 320,
            "height": 180
          },
          "high": {
            "url": "https://i.ytimg.com/vi/Df1sbXrLVx4/hqdefault.jpg",
            "width": 480,
            "height": 360
          }
        },
        "channelTitle": "Technology Gyan",
        "liveBroadcastContent": "none",
        "publishTime": "2020-08-16T12:39:20Z"
      }
    },
    {
      "kind": "youtube#searchResult",
      "etag": "EN4g947soblXWpy69gXyyTc9LDY",
      "id": {
        "kind": "youtube#video",
        "videoId": "W8ykZNSLDqE"
      },
      "snippet": {
        "publishedAt": "2019-05-23T13:45:48Z",
        "channelId": "UC4xKdmAXFh4ACyhpiQ_3qBw",
        "title": "7 Habits of Highly Effective Programmers (ft. ex-Google TechLead)",
        "description": "Ex-Google TechLead presents a holistic, integrated, principle-centered approach to programming. The first 100 people to go to ...",
        "thumbnails": {
          "default": {
            "url": "https://i.ytimg.com/vi/W8ykZNSLDqE/default.jpg",
            "width": 120,
            "height": 90
          },
          "medium": {
            "url": "https://i.ytimg.com/vi/W8ykZNSLDqE/mqdefault.jpg",
            "width": 320,
            "height": 180
          },
          "high": {
            "url": "https://i.ytimg.com/vi/W8ykZNSLDqE/hqdefault.jpg",
            "width": 480,
            "height": 360
          }
        },
        "channelTitle": "TechLead",
        "liveBroadcastContent": "none",
        "publishTime": "2019-05-23T13:45:48Z"
      }
    },
    {
      "kind": "youtube#searchResult",
      "etag": "ehHTQmti-drr-5YI4_R-M4cT4KM",
      "id": {
        "kind": "youtube#video",
        "videoId": "-jRREn6ifEQ"
      },
      "snippet": {
        "publishedAt": "2015-11-13T18:13:40Z",
        "channelId": "UCsT0YIqwnpJCM-mx7-gSA4Q",
        "title": "The poetry of programming | Linda Liukas | TEDxCERN",
        "description": "Linda Liukas believes that a movement in technology is already happening and that we need to engage everyone -- especially ...",
        "thumbnails": {
          "default": {
            "url": "https://i.ytimg.com/vi/-jRREn6ifEQ/default.jpg",
            "width": 120,
            "height": 90
          },
          "medium": {
            "url": "https://i.ytimg.com/vi/-jRREn6ifEQ/mqdefault.jpg",
            "width": 320,
            "height": 180
          },
          "high": {
            "url": "https://i.ytimg.com/vi/-jRREn6ifEQ/hqdefault.jpg",
            "width": 480,
            "height": 360
          }
        },
        "channelTitle": "TEDx Talks",
        "liveBroadcastContent": "none",
        "publishTime": "2015-11-13T18:13:40Z"
      }
    },
    {
      "kind": "youtube#searchResult",
      "etag": "k5G6bP7PDucZXl3Exp1qIg-7uGw",
      "id": {
        "kind": "youtube#video",
        "videoId": "QjMJsQx_O7o"
      },
      "snippet": {
        "publishedAt": "2021-03-12T11:00:24Z",
        "channelId": "UCWr0mx597DnSGLFk1WfvSkQ",
        "title": "What A Day In A Programmers Life Is Actually Like",
        "description": "What A Day In A Programmers Life Is Actually Like Get access to my programming courses: https://patreon.com/hallden Follow me ...",
        "thumbnails": {
          "default": {
            "url": "https://i.ytimg.com/vi/QjMJsQx_O7o/default.jpg",
            "width": 120,
            "height": 90
          },
          "medium": {
            "url": "https://i.ytimg.com/vi/QjMJsQx_O7o/mqdefault.jpg",
            "width": 320,
            "height": 180
          },
          "high": {
            "url": "https://i.ytimg.com/vi/QjMJsQx_O7o/hqdefault.jpg",
            "width": 480,
            "height": 360
          }
        },
        "channelTitle": "Kalle Hallden",
        "liveBroadcastContent": "none",
        "publishTime": "2021-03-12T11:00:24Z"
      }
    },
    {
      "kind": "youtube#searchResult",
      "etag": "FvspIPUlih9JVPCoBC_Rv0IGsOA",
      "id": {
        "kind": "youtube#video",
        "videoId": "8jLOx1hD3_o"
      },
      "snippet": {
        "publishedAt": "2022-02-17T14:45:42Z",
        "channelId": "UC8butISFwT-Wl7EV0hUK0BQ",
        "title": "C++ Programming Course - Beginner to Advanced",
        "description": "Learn modern C++ 20 programming in this comprehensive course. Source code: ...",
        "thumbnails": {
          "default": {
            "url": "https://i.ytimg.com/vi/8jLOx1hD3_o/default.jpg",
            "width": 120,
            "height": 90
          },
          "medium": {
            "url": "https://i.ytimg.com/vi/8jLOx1hD3_o/mqdefault.jpg",
            "width": 320,
            "height": 180
          },
          "high": {
            "url": "https://i.ytimg.com/vi/8jLOx1hD3_o/hqdefault.jpg",
            "width": 480,
            "height": 360
          }
        },
        "channelTitle": "freeCodeCamp.org",
        "liveBroadcastContent": "none",
        "publishTime": "2022-02-17T14:45:42Z"
      }
    },
    {
      "kind": "youtube#searchResult",
      "etag": "iMpRsNaJNPHF0oT78gRQPGVUdro",
      "id": {
        "kind": "youtube#video",
        "videoId": "J42SZXS-_Qo"
      },
      "snippet": {
        "publishedAt": "2021-11-14T21:51:05Z",
        "channelId": "UCvPPXcl5dJiBgRKGTA8inPA",
        "title": "ASMR Programming - Coding a Snake Game - No Talking",
        "description": "A snake game with Javascript! Keyboard: Skylong SK64 Red Switches (https://www.banggood.com/custlink/vKvRnGR3ht) Source ...",
        "thumbnails": {
          "default": {
            "url": "https://i.ytimg.com/vi/J42SZXS-_Qo/default.jpg",
            "width": 120,
            "height": 90
          },
          "medium": {
            "url": "https://i.ytimg.com/vi/J42SZXS-_Qo/mqdefault.jpg",
            "width": 320,
            "height": 180
          },
          "high": {
            "url": "https://i.ytimg.com/vi/J42SZXS-_Qo/hqdefault.jpg",
            "width": 480,
            "height": 360
          }
        },
        "channelTitle": "Servet Gulnaroglu",
        "liveBroadcastContent": "none",
        "publishTime": "2021-11-14T21:51:05Z"
      }
    },
    {
      "kind": "youtube#searchResult",
      "etag": "ocqk2lQqZmKyspWeGUQiSCbJRGE",
      "id": {
        "kind": "youtube#video",
        "videoId": "k9WqpQp8VSU"
      },
      "snippet": {
        "publishedAt": "2022-04-15T22:45:01Z",
        "channelId": "UCLpovxJVLBZrXJGCymB6LYw",
        "title": "How I Would Learn To Code (If I Could Start Over)",
        "description": "If I could go back in time and learn to code, I would do a lot of things differently. If I could start over, I'd spend more time doing ...",
        "thumbnails": {
          "default": {
            "url": "https://i.ytimg.com/vi/k9WqpQp8VSU/default.jpg",
            "width": 120,
            "height": 90
          },
          "medium": {
            "url": "https://i.ytimg.com/vi/k9WqpQp8VSU/mqdefault.jpg",
            "width": 320,
            "height": 180
          },
          "high": {
            "url": "https://i.ytimg.com/vi/k9WqpQp8VSU/hqdefault.jpg",
            "width": 480,
            "height": 360
          }
        },
        "channelTitle": "Namanh Kapur",
        "liveBroadcastContent": "none",
        "publishTime": "2022-04-15T22:45:01Z"
      }
    },
    {
      "kind": "youtube#searchResult",
      "etag": "kKZCeqDDgmFqa70R-smwVebSOMY",
      "id": {
        "kind": "youtube#video",
        "videoId": "hVrr438vl8g"
      },
      "snippet": {
        "publishedAt": "2021-05-29T11:30:24Z",
        "channelId": "UCN3-BVMnr44LIUheSuppw1A",
        "title": "How to Learn Python Programming Language From Basic? – [Hindi] – Quick Support",
        "description": "HowtoLearnPythonProgrammingLanguageFromBasic? #Education #QuickSupport Want to get discounts? Use the code ...",
        "thumbnails": {
          "default": {
            "url": "https://i.ytimg.com/vi/hVrr438vl8g/default.jpg",
            "width": 120,
            "height": 90
          },
          "medium": {
            "url": "https://i.ytimg.com/vi/hVrr438vl8g/mqdefault.jpg",
            "width": 320,
            "height": 180
          },
          "high": {
            "url": "https://i.ytimg.com/vi/hVrr438vl8g/hqdefault.jpg",
            "width": 480,
            "height": 360
          }
        },
        "channelTitle": "Quick Support",
        "liveBroadcastContent": "none",
        "publishTime": "2021-05-29T11:30:24Z"
      }
    },
    {
      "kind": "youtube#searchResult",
      "etag": "1vGBn892-WzdLzIuJHDiynSO_O0",
      "id": {
        "kind": "youtube#video",
        "videoId": "rpa5900OpQ4"
      },
      "snippet": {
        "publishedAt": "2020-08-03T12:09:58Z",
        "channelId": "UC1tVU8H153ZFO9eRsxdJlhA",
        "title": "How to Learn Coding for Beginners [ Sharing My Experience ]",
        "description": "How to learn coding ? coding kaise sikhe well dosto is video mein coding ke bare mein apna experience share karne wala hu ki ...",
        "thumbnails": {
          "default": {
            "url": "https://i.ytimg.com/vi/rpa5900OpQ4/default.jpg",
            "width": 120,
            "height": 90
          },
          "medium": {
            "url": "https://i.ytimg.com/vi/rpa5900OpQ4/mqdefault.jpg",
            "width": 320,
            "height": 180
          },
          "high": {
            "url": "https://i.ytimg.com/vi/rpa5900OpQ4/hqdefault.jpg",
            "width": 480,
            "height": 360
          }
        },
        "channelTitle": "Technology Gyan",
        "liveBroadcastContent": "none",
        "publishTime": "2020-08-03T12:09:58Z"
      }
    },
    {
      "kind": "youtube#searchResult",
      "etag": "bfuAsjPGSh-uLAgdfd-ak6V3o8A",
      "id": {
        "kind": "youtube#video",
        "videoId": "rfscVS0vtbw"
      },
      "snippet": {
        "publishedAt": "2018-07-11T18:00:42Z",
        "channelId": "UC8butISFwT-Wl7EV0hUK0BQ",
        "title": "Learn Python - Full Course for Beginners [Tutorial]",
        "description": "This course will give you a full introduction into all of the core concepts in python. Follow along with the videos and you'll be a ...",
        "thumbnails": {
          "default": {
            "url": "https://i.ytimg.com/vi/rfscVS0vtbw/default.jpg",
            "width": 120,
            "height": 90
          },
          "medium": {
            "url": "https://i.ytimg.com/vi/rfscVS0vtbw/mqdefault.jpg",
            "width": 320,
            "height": 180
          },
          "high": {
            "url": "https://i.ytimg.com/vi/rfscVS0vtbw/hqdefault.jpg",
            "width": 480,
            "height": 360
          }
        },
        "channelTitle": "freeCodeCamp.org",
        "liveBroadcastContent": "none",
        "publishTime": "2018-07-11T18:00:42Z"
      }
    },
    {
      "kind": "youtube#searchResult",
      "etag": "aOA1DCrgxkaj7WyUWQWhL2F_wU4",
      "id": {
        "kind": "youtube#video",
        "videoId": "pDmEYRhyusU"
      },
      "snippet": {
        "publishedAt": "2019-11-20T15:58:02Z",
        "channelId": "UCoGHeFY7jE2OB_TJS_87MOA",
        "title": "Part 1 | Introduction To Programming | C Programming Malayalam Tutorial",
        "description": "C Programming Malayalam Tutorial for Beginners This video is the part one video of the series and today we will be discussing ...",
        "thumbnails": {
          "default": {
            "url": "https://i.ytimg.com/vi/pDmEYRhyusU/default.jpg",
            "width": 120,
            "height": 90
          },
          "medium": {
            "url": "https://i.ytimg.com/vi/pDmEYRhyusU/mqdefault.jpg",
            "width": 320,
            "height": 180
          },
          "high": {
            "url": "https://i.ytimg.com/vi/pDmEYRhyusU/hqdefault.jpg",
            "width": 480,
            "height": 360
          }
        },
        "channelTitle": "Brototype Malayalam",
        "liveBroadcastContent": "none",
        "publishTime": "2019-11-20T15:58:02Z"
      }
    },
    {
      "kind": "youtube#searchResult",
      "etag": "S5zHXddSoKBAW5AgmSwmwHBKRAc",
      "id": {
        "kind": "youtube#video",
        "videoId": "sCOw5y1RQpY"
      },
      "snippet": {
        "publishedAt": "2021-11-01T13:30:15Z",
        "channelId": "UC0T6MVd3wQDB5ICAe45OxaQ",
        "title": "Python Full Tutorial for Beginners - Learn Python Programming in 17 Hours",
        "description": "In this python full tutorial for beginners, you will learn python programming in a short period with this python crash course. Python ...",
        "thumbnails": {
          "default": {
            "url": "https://i.ytimg.com/vi/sCOw5y1RQpY/default.jpg",
            "width": 120,
            "height": 90
          },
          "medium": {
            "url": "https://i.ytimg.com/vi/sCOw5y1RQpY/mqdefault.jpg",
            "width": 320,
            "height": 180
          },
          "high": {
            "url": "https://i.ytimg.com/vi/sCOw5y1RQpY/hqdefault.jpg",
            "width": 480,
            "height": 360
          }
        },
        "channelTitle": "WsCube Tech",
        "liveBroadcastContent": "none",
        "publishTime": "2021-11-01T13:30:15Z"
      }
    },
    {
      "kind": "youtube#searchResult",
      "etag": "6ASPO4IrdWRCd-5KIL7GfknDSp4",
      "id": {
        "kind": "youtube#video",
        "videoId": "_k-F-MMvQV4"
      },
      "snippet": {
        "publishedAt": "2022-05-20T15:22:05Z",
        "channelId": "UCsBjURrPoezykLs9EqgamOA",
        "title": "10 Programmer Stereotypes",
        "description": "Programmers are weird. It is human nature to put people into a box with stereotypes and the tech industry is no exception.",
        "thumbnails": {
          "default": {
            "url": "https://i.ytimg.com/vi/_k-F-MMvQV4/default.jpg",
            "width": 120,
            "height": 90
          },
          "medium": {
            "url": "https://i.ytimg.com/vi/_k-F-MMvQV4/mqdefault.jpg",
            "width": 320,
            "height": 180
          },
          "high": {
            "url": "https://i.ytimg.com/vi/_k-F-MMvQV4/hqdefault.jpg",
            "width": 480,
            "height": 360
          }
        },
        "channelTitle": "Fireship",
        "liveBroadcastContent": "none",
        "publishTime": "2022-05-20T15:22:05Z"
      }
    },
    {
      "kind": "youtube#searchResult",
      "etag": "7x01ntyo78lmi07Fq5KLbEBv88E",
      "id": {
        "kind": "youtube#video",
        "videoId": "hGIW2fDb0jg"
      },
      "snippet": {
        "publishedAt": "2020-06-29T12:51:03Z",
        "channelId": "UCMXHtrkazQjeCOteE4sof8g",
        "title": "Programming ▫️ Designing ▫️ Hacking ▫️ Coding ▫️ Focus ▫️ Music 🧬",
        "description": "Focus & Concentration (Without Vocals & high tones) SHORT DESCRIPTION I removed and smooth more aggressive or ...",
        "thumbnails": {
          "default": {
            "url": "https://i.ytimg.com/vi/hGIW2fDb0jg/default.jpg",
            "width": 120,
            "height": 90
          },
          "medium": {
            "url": "https://i.ytimg.com/vi/hGIW2fDb0jg/mqdefault.jpg",
            "width": 320,
            "height": 180
          },
          "high": {
            "url": "https://i.ytimg.com/vi/hGIW2fDb0jg/hqdefault.jpg",
            "width": 480,
            "height": 360
          }
        },
        "channelTitle": "FilFar",
        "liveBroadcastContent": "none",
        "publishTime": "2020-06-29T12:51:03Z"
      }
    }
  ]
}
